uploader/uploader.py
pyupdater_cos_plugin-0.1.1.dist-info/WHEEL
pyupdater_cos_plugin-0.1.1.dist-info/METADATA
pyupdater_cos_plugin-0.1.1.dist-info/RECORD
